pyiso20022/__init__.py
pyiso20022/admi/__init__.py
pyiso20022/admi/admi_002_001_01/__init__.py
pyiso20022/admi/admi_002_001_01/admi_002_001_01.py
pyiso20022/admi/admi_004_001_02/__init__.py
pyiso20022/admi/admi_004_001_02/admi_004_001_02.py
pyiso20022/admi/admi_006_001_01/__init__.py
pyiso20022/admi/admi_006_001_01/admi_006_001_01.py
pyiso20022/admi/admi_007_001_01/__init__.py
pyiso20022/admi/admi_007_001_01/admi_007_001_01.py
pyiso20022/admi/admi_009_001_02/__init__.py
pyiso20022/admi/admi_009_001_02/admi_009_001_02.py
pyiso20022/admi/admi_010_001_02/__init__.py
pyiso20022/admi/admi_010_001_02/admi_010_001_02.py
pyiso20022/admi/admi_011_001_01/__init__.py
pyiso20022/admi/admi_011_001_01/admi_011_001_01.py
pyiso20022/admi/admi_017_001_01/__init__.py
pyiso20022/admi/admi_017_001_01/admi_017_001_01.py
pyiso20022/camt/__init__.py
pyiso20022/camt/camt_025_001_08/__init__.py
pyiso20022/camt/camt_025_001_08/camt_025_001_08.py
pyiso20022/camt/camt_026_001_01/__init__.py
pyiso20022/camt/camt_026_001_01/camt_026_001_01.py
pyiso20022/camt/camt_026_001_03/__init__.py
pyiso20022/camt/camt_026_001_03/camt_026_001_03.py
pyiso20022/camt/camt_026_001_04/__init__.py
pyiso20022/camt/camt_026_001_04/camt_026_001_04.py
pyiso20022/camt/camt_026_001_05/__init__.py
pyiso20022/camt/camt_026_001_05/camt_026_001_05.py
pyiso20022/camt/camt_026_001_06/__init__.py
pyiso20022/camt/camt_026_001_06/camt_026_001_06.py
pyiso20022/camt/camt_026_001_07/__init__.py
pyiso20022/camt/camt_026_001_07/camt_026_001_07.py
pyiso20022/camt/camt_026_001_08/__init__.py
pyiso20022/camt/camt_026_001_08/camt_026_001_08.py
pyiso20022/camt/camt_026_001_09/__init__.py
pyiso20022/camt/camt_026_001_09/camt_026_001_09.py
pyiso20022/camt/camt_026_001_10/__init__.py
pyiso20022/camt/camt_026_001_10/camt_026_001_10.py
pyiso20022/camt/camt_028_001_01/__init__.py
pyiso20022/camt/camt_028_001_01/camt_028_001_01.py
pyiso20022/camt/camt_028_001_03/__init__.py
pyiso20022/camt/camt_028_001_03/camt_028_001_03.py
pyiso20022-1.6.2.dist-info/licenses/LICENSE
pyiso20022-1.6.2.dist-info/METADATA
pyiso20022-1.6.2.dist-info/WHEEL
pyiso20022-1.6.2.dist-info/top_level.txt
pyiso20022-1.6.2.dist-info/RECORD
