Metadata-Version: 2.4
Name: pyiso20022
Version: 1.6.2
Summary: pyiso20022 is a library for generating ISO20022 messages in Python.
Home-page: https://github.com/phoughton/pyiso20022
Author: Peter Houghton
Author-email: pete@investigatingsoftware.co.uk
Classifier: Programming Language :: Python :: 3
Classifier: License :: OSI Approved :: MIT License
Classifier: Operating System :: OS Independent
Requires-Python: >=3.8
License-File: LICENSE
Dynamic: author
Dynamic: author-email
Dynamic: classifier
Dynamic: description
Dynamic: description-content-type
Dynamic: home-page
Dynamic: license-file
Dynamic: requires-python
Dynamic: summary
